elemento_order/__init__.py
elemento_order/client.py
elemento_order/types.py
elemento_order-1.0.4.dist-info/licenses/LICENSE
elemento_order-1.0.4.dist-info/METADATA
elemento_order-1.0.4.dist-info/WHEEL
elemento_order-1.0.4.dist-info/top_level.txt
elemento_order-1.0.4.dist-info/RECORD
