Metadata-Version: 2.4
Name: elemento-order
Version: 1.0.4
Summary: Order service
Requires-Python: >=3.11
License-File: LICENSE
Requires-Dist: kaiju-tools<3,>=2.4.17
Provides-Extra: server
Requires-Dist: kaiju-db<3,>=2.3; extra == "server"
Provides-Extra: dev
Requires-Dist: kaiju-tools[dev]; extra == "dev"
Dynamic: license-file
